odoo/addons/web_clickjack_protection/README.rst
odoo/addons/web_clickjack_protection/__init__.py
odoo/addons/web_clickjack_protection/__manifest__.py
odoo/addons/web_clickjack_protection/i18n/web_clickjack_protection.pot
odoo/addons/web_clickjack_protection/readme/CONTRIBUTORS.rst
odoo/addons/web_clickjack_protection/readme/DESCRIPTION.rst
odoo/addons/web_clickjack_protection/static/description/icon.png
odoo/addons/web_clickjack_protection/static/description/index.html
odoo/addons/web_clickjack_protection/views/web_assets.xml
odoo11_addon_web_clickjack_protection-11.0.1.0.0.99.dev2.dist-info/METADATA
odoo11_addon_web_clickjack_protection-11.0.1.0.0.99.dev2.dist-info/WHEEL
odoo11_addon_web_clickjack_protection-11.0.1.0.0.99.dev2.dist-info/top_level.txt
odoo11_addon_web_clickjack_protection-11.0.1.0.0.99.dev2.dist-info/RECORD
